profuerimus/__init__.py
profuerimus/tools.py
profuerimus-0.1.1.dist-info/licenses/LICENSE
profuerimus-0.1.1.dist-info/METADATA
profuerimus-0.1.1.dist-info/WHEEL
profuerimus-0.1.1.dist-info/top_level.txt
profuerimus-0.1.1.dist-info/RECORD
