Metadata-Version: 2.4
Name: profuerimus
Version: 0.1.1
Summary: Yararlı olmuş olacağız
Author-email: Ertuğrul Taşkıran <ertugrul6taskiran@gmail.com>
Project-URL: Homepage, https://github.com/ertugrultaskiran/profuerimus
Project-URL: Bug Tracker, https://github.com/ertugrultaskiran/profuerimus/issues
Classifier: Programming Language :: Python :: 3
Classifier: License :: OSI Approved :: MIT License
Classifier: Operating System :: OS Independent
Requires-Python: >=3.7
License-File: LICENSE
Dynamic: license-file
